<Module xmlns:xsi="http://www.w3.org/2001/XMLSchema-instance" xsi:noNamespaceSchemaLocation="../FrankConfig.xsd">
    <Adapter name="ActualiseerZaakStatus"
        active="${ActualiseerZaakStatus.Active}"
        description="">
        
        <Receiver name="ActualiseerZaakStatus">
            <JavaListener name="ActualiseerZaakStatus"/>
            <JdbcErrorStorage
                name="JdbcErrorStorage"
                datasourceName="jdbc/${database.instance.name}"
                slotId="${instance.name}/actualiseerZaakStatus"/>
        </Receiver>
    
        <Pipeline>   
            <Exits>
                <Exit name="EXIT" state="SUCCESS"/>
                <Exit name="EXCEPTION" state="ERROR"/>
            </Exits>
            
            <SenderPipe
                name="CallGetZgwZaak"
                storeResultInSessionKey="GetZaakResult">
                <IbisLocalSender
                    name="CallGetZgwZaakSender"
                    javaListener="GetZgwZaak">
                    <Param name="Identificatie" xpathExpression="zakLk01/object[2]/identificatie"/>
                </IbisLocalSender>
                <Forward name="success" path="CallGetZaakTypeByZaak"/>
            </SenderPipe>

            <SenderPipe
                name="CallGetZaakTypeByZaak"
                getInputFromSessionKey="originalMessage"
                storeResultInSessionKey="GetZaakTypeResult">
                <IbisLocalSender
                    name="CallGetZgwZaakTypeSender"
                    javaListener="GetZgwZaakTypeByIdentificatie">
                    <Param name="ZaakTypeCode" xpathExpression="zakLk01/object[2]/isVan/gerelateerde/code"/>
                </IbisLocalSender>
                <Forward name="success" path="SetZgwZaakType"/>
            </SenderPipe>

            <XsltPipe
                name="SetZgwZaakType"
                styleSheetName="CreeerZaak_LK01/xsl/FilterZgwZaakTypenForGeldigheid.xslt"
                storeResultInSessionKey="GetZaakTypeResult"
                >
                <Forward name="success" path="CheckForSetZgwZaakTypeResult"/>
            </XsltPipe>

            <XmlIfPipe name="CheckForSetZgwZaakTypeResult"
                xpathExpression="count(ZgwZaakTypen/ZgwZaakType) = 1"
                >
                <Forward name="then" path="CallSetResultaatAndStatus"/>
                <Forward name="else" path="EXCEPTION"/>
            </XmlIfPipe>

            <SenderPipe
                name="CallSetResultaatAndStatus"
                getInputFromSessionKey="originalMessage"
                storeResultInSessionKey="SetResultaatAndStatusResult">
                <IbisLocalSender
                    name="CallSetResultaatAndStatusSender"
                    javaListener="SetResultaatAndStatus">
                    <Param name="ZgwZaakType" xpathExpression="$GetZaakTypeResult/ZgwZaakTypen/ZgwZaakType" type="DOMDOC">
                        <Param name="GetZaakTypeResult" sessionKey="GetZaakTypeResult" type="DOMDOC"/>
                    </Param>                   
                    <Param name="ZaakUrl" xpathExpression="$GetZaakResult/ZgwZaken/ZgwZaak/url">
                        <Param name="GetZaakResult" sessionKey="GetZaakResult" type="DOMDOC"/>
                    </Param>
                </IbisLocalSender>
                <Forward name="success" path="EXIT"/>
            </SenderPipe>
        </Pipeline>
    </Adapter>
</Module>